{
"permissions": [
	{
		"id" : 1,
		"name" : "pentadbir_full_access",
		"guard_name" : "web",
		"dibuat_oleh" : null,
		"dibuat_pada" : "2023-04-15T20:47:31.993Z",
		"dikemaskini_oleh" : null,
		"dikemaskini_pada" : null,
		"row_status" : 1,
		"is_hidden" : 0,
		"created_at" : "2023-04-16T04:47:31.997Z",
		"updated_at" : "2023-04-16T04:47:31.997Z"
	},
	{
		"id" : 2,
		"name" : "pentadbir_userlist_full",
		"guard_name" : "web",
		"dibuat_oleh" : null,
		"dibuat_pada" : "2023-04-15T20:47:32.037Z",
		"dikemaskini_oleh" : null,
		"dikemaskini_pada" : null,
		"row_status" : 1,
		"is_hidden" : 0,
		"created_at" : "2023-04-16T04:47:32.040Z",
		"updated_at" : "2023-04-16T04:47:32.040Z"
	},
	{
		"id" : 3,
		"name" : "pentadbir_userlist_view",
		"guard_name" : "web",
		"dibuat_oleh" : null,
		"dibuat_pada" : "2023-04-15T20:47:32.083Z",
		"dikemaskini_oleh" : null,
		"dikemaskini_pada" : null,
		"row_status" : 1,
		"is_hidden" : 0,
		"created_at" : "2023-04-16T04:47:32.087Z",
		"updated_at" : "2023-04-16T04:47:32.087Z"
	},
	{
		"id" : 4,
		"name" : "pentadbir_userlist_edit",
		"guard_name" : "web",
		"dibuat_oleh" : null,
		"dibuat_pada" : "2023-04-15T20:48:03.273Z",
		"dikemaskini_oleh" : null,
		"dikemaskini_pada" : null,
		"row_status" : 1,
		"is_hidden" : 0,
		"created_at" : "2023-04-16T04:48:03.277Z",
		"updated_at" : "2023-04-16T04:48:03.277Z"
	},
	{
		"id" : 5,
		"name" : "pentadbir_pengasahan-pengguna-baharu_full",
		"guard_name" : "web",
		"dibuat_oleh" : null,
		"dibuat_pada" : "2023-04-15T20:48:03.313Z",
		"dikemaskini_oleh" : null,
		"dikemaskini_pada" : null,
		"row_status" : 1,
		"is_hidden" : 0,
		"created_at" : "2023-04-16T04:48:03.317Z",
		"updated_at" : "2023-04-16T04:48:03.317Z"
	},
	{
		"id" : 6,
		"name" : "pentadbir_pengasahan-pengguna-baharu_view",
		"guard_name" : "web",
		"dibuat_oleh" : null,
		"dibuat_pada" : "2023-04-15T21:10:19.100Z",
		"dikemaskini_oleh" : null,
		"dikemaskini_pada" : null,
		"row_status" : 1,
		"is_hidden" : 0,
		"created_at" : "2023-04-16T05:10:19.100Z",
		"updated_at" : "2023-04-16T05:10:19.100Z"
	},
	{
		"id" : 7,
		"name" : "pentadbir_pengasahan-pengguna-baharu_edit",
		"guard_name" : "web",
		"dibuat_oleh" : null,
		"dibuat_pada" : "2023-04-15T21:32:54.123Z",
		"dikemaskini_oleh" : null,
		"dikemaskini_pada" : null,
		"row_status" : 1,
		"is_hidden" : 0,
		"created_at" : "2023-04-16T05:32:54.127Z",
		"updated_at" : "2023-04-16T05:32:54.127Z"
	},
	{
		"id" : 8,
		"name" : "pentadbir_daftar-pengguna-baharu_full",
		"guard_name" : "web",
		"dibuat_oleh" : null,
		"dibuat_pada" : "2023-04-15T21:32:54.180Z",
		"dikemaskini_oleh" : null,
		"dikemaskini_pada" : null,
		"row_status" : 1,
		"is_hidden" : 0,
		"created_at" : "2023-04-16T05:32:54.187Z",
		"updated_at" : "2023-04-16T05:32:54.187Z"
	},
	{
		"id" : 9,
		"name" : "pentadbir_daftar-pengguna-baharu_view",
		"guard_name" : "web",
		"dibuat_oleh" : null,
		"dibuat_pada" : "2023-04-15T21:32:54.217Z",
		"dikemaskini_oleh" : null,
		"dikemaskini_pada" : null,
		"row_status" : 1,
		"is_hidden" : 0,
		"created_at" : "2023-04-16T05:32:54.220Z",
		"updated_at" : "2023-04-16T05:32:54.220Z"
	},
	{
		"id" : 10,
		"name" : "pentadbir_daftar-pengguna-baharu_edit",
		"guard_name" : "web",
		"dibuat_oleh" : null,
		"dibuat_pada" : "2023-04-15T21:32:54.250Z",
		"dikemaskini_oleh" : null,
		"dikemaskini_pada" : null,
		"row_status" : 1,
		"is_hidden" : 0,
		"created_at" : "2023-04-16T05:32:54.257Z",
		"updated_at" : "2023-04-16T05:32:54.257Z"
	},
	{
		"id" : 11,
		"name" : "pentadbir_master/portal_full",
		"guard_name" : "web",
		"dibuat_oleh" : null,
		"dibuat_pada" : "2023-04-15T21:32:54.283Z",
		"dikemaskini_oleh" : null,
		"dikemaskini_pada" : null,
		"row_status" : 1,
		"is_hidden" : 0,
		"created_at" : "2023-04-16T05:32:54.287Z",
		"updated_at" : "2023-04-16T05:32:54.287Z"
	},
	{
		"id" : 12,
		"name" : "pentadbir_master/portal_view",
		"guard_name" : "web",
		"dibuat_oleh" : null,
		"dibuat_pada" : "2023-04-15T21:32:54.317Z",
		"dikemaskini_oleh" : null,
		"dikemaskini_pada" : null,
		"row_status" : 1,
		"is_hidden" : 0,
		"created_at" : "2023-04-16T05:32:54.320Z",
		"updated_at" : "2023-04-16T05:32:54.320Z"
	},
	{
		"id" : 13,
		"name" : "pentadbir_master/portal_edit",
		"guard_name" : "web",
		"dibuat_oleh" : null,
		"dibuat_pada" : "2023-04-15T21:32:54.350Z",
		"dikemaskini_oleh" : null,
		"dikemaskini_pada" : null,
		"row_status" : 1,
		"is_hidden" : 0,
		"created_at" : "2023-04-16T05:32:54.353Z",
		"updated_at" : "2023-04-16T05:32:54.353Z"
	},
	{
		"id" : 14,
		"name" : "pentadbir_master_full",
		"guard_name" : "web",
		"dibuat_oleh" : null,
		"dibuat_pada" : "2023-04-15T21:32:54.403Z",
		"dikemaskini_oleh" : null,
		"dikemaskini_pada" : null,
		"row_status" : 1,
		"is_hidden" : 0,
		"created_at" : "2023-04-16T05:32:54.407Z",
		"updated_at" : "2023-04-16T05:32:54.407Z"
	},
	{
		"id" : 15,
		"name" : "pentadbir_master_view",
		"guard_name" : "web",
		"dibuat_oleh" : null,
		"dibuat_pada" : "2023-04-15T21:32:54.460Z",
		"dikemaskini_oleh" : null,
		"dikemaskini_pada" : null,
		"row_status" : 1,
		"is_hidden" : 0,
		"created_at" : "2023-04-16T05:32:54.463Z",
		"updated_at" : "2023-04-16T05:32:54.463Z"
	},
	{
		"id" : 16,
		"name" : "pentadbir_master_edit",
		"guard_name" : "web",
		"dibuat_oleh" : null,
		"dibuat_pada" : "2023-04-15T21:32:54.537Z",
		"dikemaskini_oleh" : null,
		"dikemaskini_pada" : null,
		"row_status" : 1,
		"is_hidden" : 0,
		"created_at" : "2023-04-16T05:32:54.540Z",
		"updated_at" : "2023-04-16T05:32:54.540Z"
	},
	{
		"id" : 17,
		"name" : "pentadbir_Selenggara_Kod_Projek_full",
		"guard_name" : "web",
		"dibuat_oleh" : null,
		"dibuat_pada" : "2023-04-15T21:32:54.570Z",
		"dikemaskini_oleh" : null,
		"dikemaskini_pada" : null,
		"row_status" : 1,
		"is_hidden" : 0,
		"created_at" : "2023-04-16T05:32:54.573Z",
		"updated_at" : "2023-04-16T05:32:54.573Z"
	},
	{
		"id" : 18,
		"name" : "pentadbir_Selenggara_Kod_Projek_view",
		"guard_name" : "web",
		"dibuat_oleh" : null,
		"dibuat_pada" : "2023-04-15T21:32:54.620Z",
		"dikemaskini_oleh" : null,
		"dikemaskini_pada" : null,
		"row_status" : 1,
		"is_hidden" : 0,
		"created_at" : "2023-04-16T05:32:54.623Z",
		"updated_at" : "2023-04-16T05:32:54.623Z"
	},
	{
		"id" : 19,
		"name" : "pentadbir_Selenggara_Kod_Projek_edit",
		"guard_name" : "web",
		"dibuat_oleh" : null,
		"dibuat_pada" : "2023-04-15T21:32:54.663Z",
		"dikemaskini_oleh" : null,
		"dikemaskini_pada" : null,
		"row_status" : 1,
		"is_hidden" : 0,
		"created_at" : "2023-04-16T05:32:54.667Z",
		"updated_at" : "2023-04-16T05:32:54.667Z"
	},
	{
		"id" : 20,
		"name" : "pentadbir_selenggara_projek_full",
		"guard_name" : "web",
		"dibuat_oleh" : null,
		"dibuat_pada" : "2023-04-15T21:32:54.693Z",
		"dikemaskini_oleh" : null,
		"dikemaskini_pada" : null,
		"row_status" : 1,
		"is_hidden" : 0,
		"created_at" : "2023-04-16T05:32:54.697Z",
		"updated_at" : "2023-04-16T05:32:54.697Z"
	},
	{
		"id" : 21,
		"name" : "pentadbir_selenggara_projek_view",
		"guard_name" : "web",
		"dibuat_oleh" : null,
		"dibuat_pada" : "2023-04-15T21:32:54.730Z",
		"dikemaskini_oleh" : null,
		"dikemaskini_pada" : null,
		"row_status" : 1,
		"is_hidden" : 0,
		"created_at" : "2023-04-16T05:32:54.733Z",
		"updated_at" : "2023-04-16T05:32:54.733Z"
	},
	{
		"id" : 22,
		"name" : "pentadbir_selenggara_projek_edit",
		"guard_name" : "web",
		"dibuat_oleh" : null,
		"dibuat_pada" : "2023-04-15T21:32:54.787Z",
		"dikemaskini_oleh" : null,
		"dikemaskini_pada" : null,
		"row_status" : 1,
		"is_hidden" : 0,
		"created_at" : "2023-04-16T05:32:54.790Z",
		"updated_at" : "2023-04-16T05:32:54.790Z"
	},
	{
		"id" : 23,
		"name" : "pentadbir_selenggara_dashboard_analisis_full",
		"guard_name" : "web",
		"dibuat_oleh" : null,
		"dibuat_pada" : "2023-04-15T21:32:54.830Z",
		"dikemaskini_oleh" : null,
		"dikemaskini_pada" : null,
		"row_status" : 1,
		"is_hidden" : 0,
		"created_at" : "2023-04-16T05:32:54.833Z",
		"updated_at" : "2023-04-16T05:32:54.833Z"
	},
	{
		"id" : 24,
		"name" : "pentadbir_selenggara_dashboard_analisis_view",
		"guard_name" : "web",
		"dibuat_oleh" : null,
		"dibuat_pada" : "2023-04-15T21:32:54.887Z",
		"dikemaskini_oleh" : null,
		"dikemaskini_pada" : null,
		"row_status" : 1,
		"is_hidden" : 0,
		"created_at" : "2023-04-16T05:32:54.890Z",
		"updated_at" : "2023-04-16T05:32:54.890Z"
	},
	{
		"id" : 25,
		"name" : "pentadbir_selenggara_dashboard_analisis_edit",
		"guard_name" : "web",
		"dibuat_oleh" : null,
		"dibuat_pada" : "2023-04-15T21:32:54.920Z",
		"dikemaskini_oleh" : null,
		"dikemaskini_pada" : null,
		"row_status" : 1,
		"is_hidden" : 0,
		"created_at" : "2023-04-16T05:32:54.923Z",
		"updated_at" : "2023-04-16T05:32:54.923Z"
	},
	{
		"id" : 26,
		"name" : "pentadbir_selenggara_map_services_full",
		"guard_name" : "web",
		"dibuat_oleh" : null,
		"dibuat_pada" : "2023-04-15T21:32:54.950Z",
		"dikemaskini_oleh" : null,
		"dikemaskini_pada" : null,
		"row_status" : 1,
		"is_hidden" : 0,
		"created_at" : "2023-04-16T05:32:54.957Z",
		"updated_at" : "2023-04-16T05:32:54.957Z"
	},
	{
		"id" : 27,
		"name" : "pentadbir_selenggara_map_services_view",
		"guard_name" : "web",
		"dibuat_oleh" : null,
		"dibuat_pada" : "2023-04-15T21:32:54.983Z",
		"dikemaskini_oleh" : null,
		"dikemaskini_pada" : null,
		"row_status" : 1,
		"is_hidden" : 0,
		"created_at" : "2023-04-16T05:32:54.987Z",
		"updated_at" : "2023-04-16T05:32:54.987Z"
	},
	{
		"id" : 28,
		"name" : "pentadbir_selenggara_map_services_edit",
		"guard_name" : "web",
		"dibuat_oleh" : null,
		"dibuat_pada" : "2023-04-15T21:32:55.017Z",
		"dikemaskini_oleh" : null,
		"dikemaskini_pada" : null,
		"row_status" : 1,
		"is_hidden" : 0,
		"created_at" : "2023-04-16T05:32:55.023Z",
		"updated_at" : "2023-04-16T05:32:55.023Z"
	},
	{
		"id" : 29,
		"name" : "pentadbir_selenggara-pengurusan-peranan_full",
		"guard_name" : "web",
		"dibuat_oleh" : null,
		"dibuat_pada" : "2023-04-15T21:32:55.063Z",
		"dikemaskini_oleh" : null,
		"dikemaskini_pada" : null,
		"row_status" : 1,
		"is_hidden" : 0,
		"created_at" : "2023-04-16T05:32:55.067Z",
		"updated_at" : "2023-04-16T05:32:55.067Z"
	},
	{
		"id" : 30,
		"name" : "pentadbir_selenggara-pengurusan-peranan_view",
		"guard_name" : "web",
		"dibuat_oleh" : null,
		"dibuat_pada" : "2023-04-15T21:32:55.110Z",
		"dikemaskini_oleh" : null,
		"dikemaskini_pada" : null,
		"row_status" : 1,
		"is_hidden" : 0,
		"created_at" : "2023-04-16T05:32:55.110Z",
		"updated_at" : "2023-04-16T05:32:55.110Z"
	},
	{
		"id" : 31,
		"name" : "pentadbir_selenggara-pengurusan-peranan_edit",
		"guard_name" : "web",
		"dibuat_oleh" : null,
		"dibuat_pada" : "2023-04-15T21:32:55.153Z",
		"dikemaskini_oleh" : null,
		"dikemaskini_pada" : null,
		"row_status" : 1,
		"is_hidden" : 0,
		"created_at" : "2023-04-16T05:32:55.157Z",
		"updated_at" : "2023-04-16T05:32:55.157Z"
	},
	{
		"id" : 32,
		"name" : "pentadbir_audit-logs_full",
		"guard_name" : "web",
		"dibuat_oleh" : null,
		"dibuat_pada" : "2023-04-15T21:32:55.217Z",
		"dikemaskini_oleh" : null,
		"dikemaskini_pada" : null,
		"row_status" : 1,
		"is_hidden" : 0,
		"created_at" : "2023-04-16T05:32:55.220Z",
		"updated_at" : "2023-04-16T05:32:55.220Z"
	},
	{
		"id" : 33,
		"name" : "pentadbir_audit-logs_view",
		"guard_name" : "web",
		"dibuat_oleh" : null,
		"dibuat_pada" : "2023-04-15T21:32:55.310Z",
		"dikemaskini_oleh" : null,
		"dikemaskini_pada" : null,
		"row_status" : 1,
		"is_hidden" : 0,
		"created_at" : "2023-04-16T05:32:55.313Z",
		"updated_at" : "2023-04-16T05:32:55.313Z"
	},
	{
		"id" : 34,
		"name" : "pentadbir_audit-logs_edit",
		"guard_name" : "web",
		"dibuat_oleh" : null,
		"dibuat_pada" : "2023-04-15T21:32:55.413Z",
		"dikemaskini_oleh" : null,
		"dikemaskini_pada" : null,
		"row_status" : 1,
		"is_hidden" : 0,
		"created_at" : "2023-04-16T05:32:55.413Z",
		"updated_at" : "2023-04-16T05:32:55.413Z"
	},
	{
		"id" : 35,
		"name" : "pentadbir_home_full",
		"guard_name" : "web",
		"dibuat_oleh" : null,
		"dibuat_pada" : "2023-04-15T21:32:55.517Z",
		"dikemaskini_oleh" : null,
		"dikemaskini_pada" : null,
		"row_status" : 1,
		"is_hidden" : 0,
		"created_at" : "2023-04-16T05:32:55.520Z",
		"updated_at" : "2023-04-16T05:32:55.520Z"
	},
	{
		"id" : 36,
		"name" : "pentadbir_home_view",
		"guard_name" : "web",
		"dibuat_oleh" : null,
		"dibuat_pada" : "2023-04-15T21:32:55.743Z",
		"dikemaskini_oleh" : null,
		"dikemaskini_pada" : null,
		"row_status" : 1,
		"is_hidden" : 0,
		"created_at" : "2023-04-16T05:32:55.747Z",
		"updated_at" : "2023-04-16T05:32:55.747Z"
	},
	{
		"id" : 37,
		"name" : "pentadbir_home_edit",
		"guard_name" : "web",
		"dibuat_oleh" : null,
		"dibuat_pada" : "2023-04-15T21:32:56.250Z",
		"dikemaskini_oleh" : null,
		"dikemaskini_pada" : null,
		"row_status" : 1,
		"is_hidden" : 0,
		"created_at" : "2023-04-16T05:32:56.253Z",
		"updated_at" : "2023-04-16T05:32:56.253Z"
	},
	{
		"id" : 38,
		"name" : "permohon_full_access",
		"guard_name" : "web",
		"dibuat_oleh" : null,
		"dibuat_pada" : "2023-04-15T21:32:56.607Z",
		"dikemaskini_oleh" : null,
		"dikemaskini_pada" : null,
		"row_status" : 1,
		"is_hidden" : 0,
		"created_at" : "2023-04-16T05:32:56.607Z",
		"updated_at" : "2023-04-16T05:32:56.607Z"
	},
	{
		"id" : 39,
		"name" : "permohon_parmohonan-project-dashboard_full",
		"guard_name" : "web",
		"dibuat_oleh" : null,
		"dibuat_pada" : "2023-04-15T21:32:56.640Z",
		"dikemaskini_oleh" : null,
		"dikemaskini_pada" : null,
		"row_status" : 1,
		"is_hidden" : 0,
		"created_at" : "2023-04-16T05:32:56.640Z",
		"updated_at" : "2023-04-16T05:32:56.640Z"
	},
	{
		"id" : 40,
		"name" : "permohon_parmohonan-project-dashboard_view",
		"guard_name" : "web",
		"dibuat_oleh" : null,
		"dibuat_pada" : "2023-04-15T21:32:56.673Z",
		"dikemaskini_oleh" : null,
		"dikemaskini_pada" : null,
		"row_status" : 1,
		"is_hidden" : 0,
		"created_at" : "2023-04-16T05:32:56.673Z",
		"updated_at" : "2023-04-16T05:32:56.673Z"
	},
	{
		"id" : 41,
		"name" : "permohon_parmohonan-project-dashboard_edit",
		"guard_name" : "web",
		"dibuat_oleh" : null,
		"dibuat_pada" : "2023-04-15T21:32:56.707Z",
		"dikemaskini_oleh" : null,
		"dikemaskini_pada" : null,
		"row_status" : 1,
		"is_hidden" : 0,
		"created_at" : "2023-04-16T05:32:56.707Z",
		"updated_at" : "2023-04-16T05:32:56.707Z"
	},
	{
		"id" : 42,
		"name" : "permohon_project-list_full",
		"guard_name" : "web",
		"dibuat_oleh" : null,
		"dibuat_pada" : "2023-04-15T21:32:56.750Z",
		"dikemaskini_oleh" : null,
		"dikemaskini_pada" : null,
		"row_status" : 1,
		"is_hidden" : 0,
		"created_at" : "2023-04-16T05:32:56.753Z",
		"updated_at" : "2023-04-16T05:32:56.753Z"
	},
	{
		"id" : 43,
		"name" : "permohon_project-list_view",
		"guard_name" : "web",
		"dibuat_oleh" : null,
		"dibuat_pada" : "2023-04-15T21:32:56.797Z",
		"dikemaskini_oleh" : null,
		"dikemaskini_pada" : null,
		"row_status" : 1,
		"is_hidden" : 0,
		"created_at" : "2023-04-16T05:32:56.797Z",
		"updated_at" : "2023-04-16T05:32:56.797Z"
	},
	{
		"id" : 44,
		"name" : "permohon_project-list_edit",
		"guard_name" : "web",
		"dibuat_oleh" : null,
		"dibuat_pada" : "2023-04-15T21:32:56.840Z",
		"dikemaskini_oleh" : null,
		"dikemaskini_pada" : null,
		"row_status" : 1,
		"is_hidden" : 0,
		"created_at" : "2023-04-16T05:32:56.840Z",
		"updated_at" : "2023-04-16T05:32:56.840Z"
	},
	{
		"id" : 45,
		"name" : "permohon_salin-project-list_full",
		"guard_name" : "web",
		"dibuat_oleh" : null,
		"dibuat_pada" : "2023-04-15T21:32:56.897Z",
		"dikemaskini_oleh" : null,
		"dikemaskini_pada" : null,
		"row_status" : 1,
		"is_hidden" : 0,
		"created_at" : "2023-04-16T05:32:56.897Z",
		"updated_at" : "2023-04-16T05:32:56.897Z"
	},
	{
		"id" : 46,
		"name" : "permohon_salin-project-list_view",
		"guard_name" : "web",
		"dibuat_oleh" : null,
		"dibuat_pada" : "2023-04-15T21:32:56.940Z",
		"dikemaskini_oleh" : null,
		"dikemaskini_pada" : null,
		"row_status" : 1,
		"is_hidden" : 0,
		"created_at" : "2023-04-16T05:32:56.940Z",
		"updated_at" : "2023-04-16T05:32:56.940Z"
	},
	{
		"id" : 47,
		"name" : "permohon_salin-project-list_edit",
		"guard_name" : "web",
		"dibuat_oleh" : null,
		"dibuat_pada" : "2023-04-15T21:32:56.983Z",
		"dikemaskini_oleh" : null,
		"dikemaskini_pada" : null,
		"row_status" : 1,
		"is_hidden" : 0,
		"created_at" : "2023-04-16T05:32:56.987Z",
		"updated_at" : "2023-04-16T05:32:56.987Z"
	},
	{
		"id" : 48,
		"name" : "permohon_semak-project-list_full",
		"guard_name" : "web",
		"dibuat_oleh" : null,
		"dibuat_pada" : "2023-04-15T21:32:57.027Z",
		"dikemaskini_oleh" : null,
		"dikemaskini_pada" : null,
		"row_status" : 1,
		"is_hidden" : 0,
		"created_at" : "2023-04-16T05:32:57.030Z",
		"updated_at" : "2023-04-16T05:32:57.030Z"
	},
	{
		"id" : 49,
		"name" : "permohon_semak-project-list_view",
		"guard_name" : "web",
		"dibuat_oleh" : null,
		"dibuat_pada" : "2023-04-15T21:32:57.073Z",
		"dikemaskini_oleh" : null,
		"dikemaskini_pada" : null,
		"row_status" : 1,
		"is_hidden" : 0,
		"created_at" : "2023-04-16T05:32:57.073Z",
		"updated_at" : "2023-04-16T05:32:57.073Z"
	},
	{
		"id" : 50,
		"name" : "permohon_semak-project-list_edit",
		"guard_name" : "web",
		"dibuat_oleh" : null,
		"dibuat_pada" : "2023-04-15T21:32:57.117Z",
		"dikemaskini_oleh" : null,
		"dikemaskini_pada" : null,
		"row_status" : 1,
		"is_hidden" : 0,
		"created_at" : "2023-04-16T05:32:57.120Z",
		"updated_at" : "2023-04-16T05:32:57.120Z"
	},
	{
		"id" : 51,
		"name" : "permohon_janaan_laporan_full",
		"guard_name" : "web",
		"dibuat_oleh" : null,
		"dibuat_pada" : "2023-04-15T21:32:57.160Z",
		"dikemaskini_oleh" : null,
		"dikemaskini_pada" : null,
		"row_status" : 1,
		"is_hidden" : 0,
		"created_at" : "2023-04-16T05:32:57.163Z",
		"updated_at" : "2023-04-16T05:32:57.163Z"
	},
	{
		"id" : 52,
		"name" : "permohon_janaan_laporan_view",
		"guard_name" : "web",
		"dibuat_oleh" : null,
		"dibuat_pada" : "2023-04-15T21:32:57.193Z",
		"dikemaskini_oleh" : null,
		"dikemaskini_pada" : null,
		"row_status" : 1,
		"is_hidden" : 0,
		"created_at" : "2023-04-16T05:32:57.197Z",
		"updated_at" : "2023-04-16T05:32:57.197Z"
	},
	{
		"id" : 53,
		"name" : "permohon_janaan_laporan_edit",
		"guard_name" : "web",
		"dibuat_oleh" : null,
		"dibuat_pada" : "2023-04-15T21:32:57.227Z",
		"dikemaskini_oleh" : null,
		"dikemaskini_pada" : null,
		"row_status" : 1,
		"is_hidden" : 0,
		"created_at" : "2023-04-16T05:32:57.230Z",
		"updated_at" : "2023-04-16T05:32:57.230Z"
	},
	{
		"id" : 54,
		"name" : "vm_full_access",
		"guard_name" : "web",
		"dibuat_oleh" : null,
		"dibuat_pada" : "2023-04-15T21:32:57.260Z",
		"dikemaskini_oleh" : null,
		"dikemaskini_pada" : null,
		"row_status" : 1,
		"is_hidden" : 0,
		"created_at" : "2023-04-16T05:32:57.263Z",
		"updated_at" : "2023-04-16T05:32:57.263Z"
	},
	{
		"id" : 55,
		"name" : "vm_fasilitator_full",
		"guard_name" : "web",
		"dibuat_oleh" : null,
		"dibuat_pada" : "2023-04-15T21:32:57.303Z",
		"dikemaskini_oleh" : null,
		"dikemaskini_pada" : null,
		"row_status" : 1,
		"is_hidden" : 0,
		"created_at" : "2023-04-16T05:32:57.307Z",
		"updated_at" : "2023-04-16T05:32:57.307Z"
	},
	{
		"id" : 56,
		"name" : "vm_fasilitator_view",
		"guard_name" : "web",
		"dibuat_oleh" : null,
		"dibuat_pada" : "2023-04-15T21:32:57.350Z",
		"dikemaskini_oleh" : null,
		"dikemaskini_pada" : null,
		"row_status" : 1,
		"is_hidden" : 0,
		"created_at" : "2023-04-16T05:32:57.353Z",
		"updated_at" : "2023-04-16T05:32:57.353Z"
	},
	{
		"id" : 57,
		"name" : "vm_fasilitator_edit",
		"guard_name" : "web",
		"dibuat_oleh" : null,
		"dibuat_pada" : "2023-04-15T21:32:57.413Z",
		"dikemaskini_oleh" : null,
		"dikemaskini_pada" : null,
		"row_status" : 1,
		"is_hidden" : 0,
		"created_at" : "2023-04-16T05:32:57.417Z",
		"updated_at" : "2023-04-16T05:32:57.417Z"
	},
	{
		"id" : 58,
		"name" : "vm_KalendarVM_full",
		"guard_name" : "web",
		"dibuat_oleh" : null,
		"dibuat_pada" : "2023-04-15T21:32:57.447Z",
		"dikemaskini_oleh" : null,
		"dikemaskini_pada" : null,
		"row_status" : 1,
		"is_hidden" : 0,
		"created_at" : "2023-04-16T05:32:57.453Z",
		"updated_at" : "2023-04-16T05:32:57.453Z"
	},
	{
		"id" : 59,
		"name" : "vm_KalendarVM_view",
		"guard_name" : "web",
		"dibuat_oleh" : null,
		"dibuat_pada" : "2023-04-15T21:32:57.490Z",
		"dikemaskini_oleh" : null,
		"dikemaskini_pada" : null,
		"row_status" : 1,
		"is_hidden" : 0,
		"created_at" : "2023-04-16T05:32:57.493Z",
		"updated_at" : "2023-04-16T05:32:57.493Z"
	},
	{
		"id" : 60,
		"name" : "vm_KalendarVM_edit",
		"guard_name" : "web",
		"dibuat_oleh" : null,
		"dibuat_pada" : "2023-04-15T21:48:10.113Z",
		"dikemaskini_oleh" : null,
		"dikemaskini_pada" : null,
		"row_status" : 1,
		"is_hidden" : 0,
		"created_at" : "2023-04-16T05:48:10.120Z",
		"updated_at" : "2023-04-16T05:48:10.120Z"
	},
	{
		"id" : 61,
		"name" : "vm_senarai_selasai_makmal_full",
		"guard_name" : "web",
		"dibuat_oleh" : null,
		"dibuat_pada" : "2023-04-15T21:48:32.360Z",
		"dikemaskini_oleh" : null,
		"dikemaskini_pada" : null,
		"row_status" : 1,
		"is_hidden" : 0,
		"created_at" : "2023-04-16T05:48:32.363Z",
		"updated_at" : "2023-04-16T05:48:32.363Z"
	},
	{
		"id" : 62,
		"name" : "vm_senarai_selasai_makmal_view",
		"guard_name" : "web",
		"dibuat_oleh" : null,
		"dibuat_pada" : "2023-04-15T21:48:32.460Z",
		"dikemaskini_oleh" : null,
		"dikemaskini_pada" : null,
		"row_status" : 1,
		"is_hidden" : 0,
		"created_at" : "2023-04-16T05:48:32.463Z",
		"updated_at" : "2023-04-16T05:48:32.463Z"
	},
	{
		"id" : 63,
		"name" : "vm_senarai_selasai_makmal_edit",
		"guard_name" : "web",
		"dibuat_oleh" : null,
		"dibuat_pada" : "2023-04-15T21:48:32.523Z",
		"dikemaskini_oleh" : null,
		"dikemaskini_pada" : null,
		"row_status" : 1,
		"is_hidden" : 0,
		"created_at" : "2023-04-16T05:48:32.527Z",
		"updated_at" : "2023-04-16T05:48:32.527Z"
	},
	{
		"id" : 64,
		"name" : "vm_senarai_makmal_and_mini_full",
		"guard_name" : "web",
		"dibuat_oleh" : null,
		"dibuat_pada" : "2023-04-15T21:48:32.560Z",
		"dikemaskini_oleh" : null,
		"dikemaskini_pada" : null,
		"row_status" : 1,
		"is_hidden" : 0,
		"created_at" : "2023-04-16T05:48:32.563Z",
		"updated_at" : "2023-04-16T05:48:32.563Z"
	},
	{
		"id" : 65,
		"name" : "vm_senarai_makmal_and_mini_view",
		"guard_name" : "web",
		"dibuat_oleh" : null,
		"dibuat_pada" : "2023-04-15T21:48:32.593Z",
		"dikemaskini_oleh" : null,
		"dikemaskini_pada" : null,
		"row_status" : 1,
		"is_hidden" : 0,
		"created_at" : "2023-04-16T05:48:32.597Z",
		"updated_at" : "2023-04-16T05:48:32.597Z"
	},
	{
		"id" : 66,
		"name" : "vm_senarai_makmal_and_mini_edit",
		"guard_name" : "web",
		"dibuat_oleh" : null,
		"dibuat_pada" : "2023-04-15T21:48:32.593Z",
		"dikemaskini_oleh" : null,
		"dikemaskini_pada" : null,
		"row_status" : 1,
		"is_hidden" : 0,
		"created_at" : "2023-04-16T05:48:32.597Z",
		"updated_at" : "2023-04-16T05:48:32.597Z"
	},
	{
		"id" : 67,
		"name" : "permantuan_full_access",
		"guard_name" : "web",
		"dibuat_oleh" : null,
		"dibuat_pada" : "2023-04-15T21:48:32.593Z",
		"dikemaskini_oleh" : null,
		"dikemaskini_pada" : null,
		"row_status" : 1,
		"is_hidden" : 0,
		"created_at" : "2023-04-16T05:48:32.597Z",
		"updated_at" : "2023-04-16T05:48:32.597Z"
	},
	{
		"id" : 68,
		"name" : "kontrak_full_access",
		"guard_name" : "web",
		"dibuat_oleh" : null,
		"dibuat_pada" : "2023-04-15T21:48:32.593Z",
		"dikemaskini_oleh" : null,
		"dikemaskini_pada" : null,
		"row_status" : 1,
		"is_hidden" : 0,
		"created_at" : "2023-04-16T05:48:32.597Z",
		"updated_at" : "2023-04-16T05:48:32.597Z"
	},
	{
		"id" : 69,
		"name" : "peruding_full_access",
		"guard_name" : "web",
		"dibuat_oleh" : null,
		"dibuat_pada" : "2023-04-15T21:48:32.593Z",
		"dikemaskini_oleh" : null,
		"dikemaskini_pada" : null,
		"row_status" : 1,
		"is_hidden" : 0,
		"created_at" : "2023-04-16T05:48:32.597Z",
		"updated_at" : "2023-04-16T05:48:32.597Z"
	},
	{
		"id" : 70,
		"name" : "permohon_daftar-permohonan-project_full",
		"guard_name" : "web",
		"dibuat_oleh" : null,
		"dibuat_pada" : "2023-04-15T21:48:32.593Z",
		"dikemaskini_oleh" : null,
		"dikemaskini_pada" : null,
		"row_status" : 1,
		"is_hidden" : 0,
		"created_at" : "2023-04-16T05:48:32.597Z",
		"updated_at" : "2023-04-16T05:48:32.597Z"
	},
	{
		"id" : 71,
		"name" : "permohon_daftar-permohonan-project_edit",
		"guard_name" : "web",
		"dibuat_oleh" : null,
		"dibuat_pada" : "2023-04-15T21:48:32.593Z",
		"dikemaskini_oleh" : null,
		"dikemaskini_pada" : null,
		"row_status" : 1,
		"is_hidden" : 0,
		"created_at" : "2023-04-16T05:48:32.597Z",
		"updated_at" : "2023-04-16T05:48:32.597Z"
	},
	{
		"id" : 72,
		"name" : "permohon_daftar-permohonan-project_view",
		"guard_name" : "web",
		"dibuat_oleh" : null,
		"dibuat_pada" : "2023-04-15T21:48:32.593Z",
		"dikemaskini_oleh" : null,
		"dikemaskini_pada" : null,
		"row_status" : 1,
		"is_hidden" : 0,
		"created_at" : "2023-04-16T05:48:32.597Z",
		"updated_at" : "2023-04-16T05:48:32.597Z"
	},
	{
		"id" : 73,
		"name" : "noc_full_access",
		"guard_name" : "web",
		"dibuat_oleh" : null,
		"dibuat_pada" : "2023-04-15T21:48:32.593Z",
		"dikemaskini_oleh" : null,
		"dikemaskini_pada" : null,
		"row_status" : 1,
		"is_hidden" : 0,
		"created_at" : "2023-04-16T05:48:32.597Z",
		"updated_at" : "2023-04-16T05:48:32.597Z"
	},
	{
		"id" : 74,
		"name" : "rp_full_access",
		"guard_name" : "web",
		"dibuat_oleh" : null,
		"dibuat_pada" : "2023-04-15T21:48:32.593Z",
		"dikemaskini_oleh" : null,
		"dikemaskini_pada" : null,
		"row_status" : 1,
		"is_hidden" : 0,
		"created_at" : "2023-04-16T05:48:32.597Z",
		"updated_at" : "2023-04-16T05:48:32.597Z"
	},
	{
		"id" : 75,
		"name" : "pl_full_access",
		"guard_name" : "web",
		"dibuat_oleh" : null,
		"dibuat_pada" : "2023-04-15T21:48:32.593Z",
		"dikemaskini_oleh" : null,
		"dikemaskini_pada" : null,
		"row_status" : 1,
		"is_hidden" : 0,
		"created_at" : "2023-04-16T05:48:32.597Z"
	}
	
]}
